{
  "paragraphs": [
    {
      "text": "%md\n\n### Title of this Notebook",
      "user": "anonymous",
      "dateUpdated": "May 27, 2018 11:18:10 PM",
      "config": {
        "colWidth": 12.0,
        "enabled": true,
        "results": {},
        "editorSetting": {
          "language": "markdown",
          "editOnDblClick": true
        },
        "editorMode": "ace/mode/markdown",
        "editorHide": true,
        "tableHide": false
      },
      "settings": {
        "params": {},
        "forms": {}
      },
      "results": {
        "code": "SUCCESS",
        "msg": [
          {
            "type": "HTML",
            "data": "\u003cdiv class\u003d\"markdown-body\"\u003e\n\u003ch3\u003eTitle of this Notebook\u003c/h3\u003e\n\u003c/div\u003e"
          }
        ]
      },
      "apps": [],
      "jobName": "paragraph_1527462903769_402481370",
      "id": "20180527-231503_1776598203",
      "dateCreated": "May 27, 2018 11:15:03 PM",
      "dateStarted": "May 27, 2018 11:18:10 PM",
      "dateFinished": "May 27, 2018 11:18:10 PM",
      "status": "FINISHED",
      "progressUpdateIntervalMs": 500
    },
    {
      "text": "%md\n",
      "user": "anonymous",
      "dateUpdated": "May 27, 2018 11:18:06 PM",
      "config": {
        "colWidth": 12.0,
        "enabled": true,
        "results": {},
        "editorSetting": {
          "language": "markdown",
          "editOnDblClick": true
        },
        "editorMode": "ace/mode/markdown"
      },
      "settings": {
        "params": {},
        "forms": {}
      },
      "apps": [],
      "jobName": "paragraph_1527462921018_1826098273",
      "id": "20180527-231521_1409735610",
      "dateCreated": "May 27, 2018 11:15:21 PM",
      "status": "FINISHED",
      "progressUpdateIntervalMs": 500
    }
  ],
  "name": "/Tests/Note1",
  "id": "2DE2UGAFG",
  "angularObjects": {
    "2DG7M41E9:shared_process": [],
    "2DHE1WGQ1:shared_process": [],
    "2DE5SEBWN:shared_process": [],
    "2DG27QMGX:shared_process": [],
    "2DDKA2SDH:shared_process": [],
    "2DGGM5BYV:shared_process": [],
    "2DFVCNZ63:shared_process": [],
    "2DGWN7R8V:shared_process": [],
    "2DFYFKVKX:shared_process": [],
    "2DFFETUSW:shared_process": [],
    "2DENS6M4R:shared_process": [],
    "2DGQ9GVGH:shared_process": [],
    "2DFP42S81:shared_process": [],
    "2DGMUUX3D:shared_process": [],
    "2DFW92P5P:shared_process": [],
    "2DFJP8AA3:shared_process": [],
    "2DGGMXPMY:shared_process": [],
    "2DEQE9PHN:shared_process": [],
    "2DFUWBA5Z:shared_process": []
  },
  "config": {},
  "info": {}
}